hyperkuutio/__init__.py
hyperkuutio/__main__.py
hyperkuutio/cli.py
hyperkuutio/hyperkuutio.py
hyperkuutio-2023.10.29.dist-info/LICENSE
hyperkuutio-2023.10.29.dist-info/METADATA
hyperkuutio-2023.10.29.dist-info/WHEEL
hyperkuutio-2023.10.29.dist-info/entry_points.txt
hyperkuutio-2023.10.29.dist-info/top_level.txt
hyperkuutio-2023.10.29.dist-info/RECORD
