Metadata-Version: 2.1
Name: hyperkuutio
Version: 2023.10.29
Summary: Hypercube (Finnish: hyperkuutio) tool that scratches some itch.
Author-email: Stefan Hagen <stefan@hagen.link>
Maintainer-email: Stefan Hagen <stefan@hagen.link>
Project-URL: Homepage, https://git.sr.ht/~sthagen/hyperkuutio
Project-URL: Bug-Tracker, https://todo.sr.ht/~sthagen/hyperkuutio
Project-URL: Documentation, https://codes.dilettant.life/docs/hyperkuutio
Project-URL: Source-Code, https://git.sr.ht/~sthagen/hyperkuutio
Project-URL: Test-Coverage, https://codes.dilettant.life/coverage/hyperkuutio
Keywords: developer-tools,validation,verification
Classifier: Development Status :: 3 - Alpha
Classifier: Intended Audience :: Developers
Classifier: License :: OSI Approved :: MIT License
Classifier: Programming Language :: Python :: 3.10
Classifier: Programming Language :: Python :: 3.11
Classifier: Programming Language :: Python :: 3.12
Classifier: Programming Language :: Python :: 3.9
Requires-Python: >=3.9
License-File: LICENSE
Requires-Dist: openpyxl >=3.1.2
Requires-Dist: pandas >=2.1.2
Requires-Dist: pydantic >=2.4.2
Requires-Dist: typer >=0.9.0
Provides-Extra: dev
Requires-Dist: black ; extra == 'dev'
Requires-Dist: coverage ; extra == 'dev'
Requires-Dist: hypothesis ; extra == 'dev'
Requires-Dist: mypy ; extra == 'dev'
Requires-Dist: pytest ; extra == 'dev'
Requires-Dist: pytest-cov ; extra == 'dev'
Requires-Dist: pytest-flake8 ; extra == 'dev'
Requires-Dist: ruff ; extra == 'dev'
